userprovided/__init__.py
userprovided/_version.py
userprovided/date.py
userprovided/err.py
userprovided/hash.py
userprovided/hashing.py
userprovided/mail.py
userprovided/parameters.py
userprovided/py.typed
userprovided/url.py
userprovided-0.9.4.dist-info/LICENSE
userprovided-0.9.4.dist-info/METADATA
userprovided-0.9.4.dist-info/WHEEL
userprovided-0.9.4.dist-info/top_level.txt
userprovided-0.9.4.dist-info/RECORD
