Metadata-Version: 2.1
Name: userprovided
Version: 0.9.4
Summary: A library to check user input for validity and / or plausibility
Home-page: https://github.com/RuedigerVoigt/userprovided
Author: Rüdiger Voigt
Author-email: projects@ruediger-voigt.eu
License: UNKNOWN
Platform: UNKNOWN
Classifier: Programming Language :: Python :: 3
Classifier: Programming Language :: Python :: 3.6
Classifier: Programming Language :: Python :: 3.7
Classifier: Programming Language :: Python :: 3.8
Classifier: Programming Language :: Python :: 3.9
Classifier: Programming Language :: Python :: 3.10
Classifier: License :: OSI Approved :: Apache Software License
Classifier: Operating System :: OS Independent
Classifier: Development Status :: 5 - Production/Stable
Classifier: Intended Audience :: Science/Research
Classifier: Intended Audience :: Developers
Classifier: Topic :: Security
Classifier: Topic :: Utilities
Classifier: Topic :: Software Development :: Quality Assurance
Requires-Python: >=3.6
